{
  "normal_pz_s2": [
    {
      "a_region": "normal_pz_s2",
      "snr": 257.08704751503916,
      "patient_key": "new02",
      "gs": "4+3",
      "target": "3",
      "patient_age": "NaN",
      "diffusivities": [
        0.25,
        0.5,
        0.75,
        1.0,
        1.25,
        1.5,
        2.0,
        2.5,
        3.0,
        20.0
      ],
      "hdf5_dataset": "new02_roi2"
    },
    {
      "a_region": "normal_pz_s2",
      "snr": 641.8966038233884,
      "patient_key": "new03",
      "gs": "4+3+5",
      "target": "5",
      "patient_age": "NaN",
      "diffusivities": [
        0.25,
        0.5,
        0.75,
        1.0,
        1.25,
        1.5,
        2.0,
        2.5,
        3.0,
        20.0
      ],
      "hdf5_dataset": "new03_roi2"
    },
    {
      "a_region": "normal_pz_s2",
      "snr": 543.4266279821039,
      "patient_key": "new04",
      "gs": "3+4",
      "target": "2",
      "patient_age": "NaN",
      "diffusivities": [
        0.25,
        0.5,
        0.75,
        1.0,
        1.25,
        1.5,
        2.0,
        2.5,
        3.0,
        20.0
      ],
      "hdf5_dataset": "new04_roi2"
    },
    {
      "a_region": "normal_pz_s2",
      "snr": 520.9666496043676,
      "patient_key": "new07",
      "gs": "3+3",
      "target": "1",
      "patient_age": "NaN",
      "diffusivities": [
        0.25,
        0.5,
        0.75,
        1.0,
        1.25,
        1.5,
        2.0,
        2.5,
        3.0,
        20.0
      ],
      "hdf5_dataset": "new07_roi2"
    },
    {
      "a_region": "normal_pz_s2",
      "snr": 435.7106264483344,
      "patient_key": "new12",
      "gs": "hgpin",
      "target": "hgpin",
      "patient_age": "NaN",
      "diffusivities": [
        0.25,
        0.5,
        0.75,
        1.0,
        1.25,
        1.5,
        2.0,
        2.5,
        3.0,
        20.0
      ],
      "hdf5_dataset": "new12_roi2"
    },
    {
      "a_region": "normal_pz_s2",
      "snr": 380.5834336909582,
      "patient_key": "new16",
      "gs": "3+4",
      "target": "2",
      "patient_age": "NaN",
      "diffusivities": [
        0.25,
        0.5,
        0.75,
        1.0,
        1.25,
        1.5,
        2.0,
        2.5,
        3.0,
        20.0
      ],
      "hdf5_dataset": "new16_roi2"
    },
    {
      "a_region": "normal_pz_s2",
      "snr": 295.27529527544294,
      "patient_key": "new18",
      "gs": "4+3",
      "target": "3",
      "patient_age": "NaN",
      "diffusivities": [
        0.25,
        0.5,
        0.75,
        1.0,
        1.25,
        1.5,
        2.0,
        2.5,
        3.0,
        20.0
      ],
      "hdf5_dataset": "new18_roi2"
    },
    {
      "a_region": "normal_pz_s2",
      "snr": 527.6717729801358,
      "patient_key": "new21",
      "gs": "3+4",
      "target": "2",
      "patient_age": "NaN",
      "diffusivities": [
        0.25,
        0.5,
        0.75,
        1.0,
        1.25,
        1.5,
        2.0,
        2.5,
        3.0,
        20.0
      ],
      "hdf5_dataset": "new21_roi2"
    },
    {
      "a_region": "normal_pz_s2",
      "snr": 474.3416490252569,
      "patient_key": "new22",
      "gs": "0+0",
      "target": "0",
      "patient_age": "NaN",
      "diffusivities": [
        0.25,
        0.5,
        0.75,
        1.0,
        1.25,
        1.5,
        2.0,
        2.5,
        3.0,
        20.0
      ],
      "hdf5_dataset": "new22_roi2"
    },
    {
      "a_region": "normal_pz_s2",
      "snr": 409.0767042988393,
      "patient_key": "new23",
      "gs": "0+0",
      "target": "0",
      "patient_age": "NaN",
      "diffusivities": [
        0.25,
        0.5,
        0.75,
        1.0,
        1.25,
        1.5,
        2.0,
        2.5,
        3.0,
        20.0
      ],
      "hdf5_dataset": "new23_roi2"
    },
    {
      "a_region": "normal_pz_s2",
      "snr": 422.60353760942417,
      "patient_key": "new24",
      "gs": "0+0",
      "target": "0",
      "patient_age": "NaN",
      "diffusivities": [
        0.25,
        0.5,
        0.75,
        1.0,
        1.25,
        1.5,
        2.0,
        2.5,
        3.0,
        20.0
      ],
      "hdf5_dataset": "new24_roi2"
    },
    {
      "a_region": "normal_pz_s2",
      "snr": 483.1537022521922,
      "patient_key": "new26",
      "gs": "nan",
      "target": "nan",
      "patient_age": "NaN",
      "diffusivities": [
        0.25,
        0.5,
        0.75,
        1.0,
        1.25,
        1.5,
        2.0,
        2.5,
        3.0,
        20.0
      ],
      "hdf5_dataset": "new26_roi2"
    },
    {
      "a_region": "normal_pz_s2",
      "snr": 335.4101966249685,
      "patient_key": "new30",
      "gs": "3+4",
      "target": "2",
      "patient_age": "NaN",
      "diffusivities": [
        0.25,
        0.5,
        0.75,
        1.0,
        1.25,
        1.5,
        2.0,
        2.5,
        3.0,
        20.0
      ],
      "hdf5_dataset": "new30_roi2"
    },
    {
      "a_region": "normal_pz_s2",
      "snr": 548.5777064372922,
      "patient_key": "new33",
      "gs": "3+3",
      "target": "1",
      "patient_age": "NaN",
      "diffusivities": [
        0.25,
        0.5,
        0.75,
        1.0,
        1.25,
        1.5,
        2.0,
        2.5,
        3.0,
        20.0
      ],
      "hdf5_dataset": "new33_roi2"
    },
    {
      "a_region": "normal_pz_s2",
      "snr": 553.6808647587525,
      "patient_key": "new34",
      "gs": "3+4",
      "target": "2",
      "patient_age": "NaN",
      "diffusivities": [
        0.25,
        0.5,
        0.75,
        1.0,
        1.25,
        1.5,
        2.0,
        2.5,
        3.0,
        20.0
      ],
      "hdf5_dataset": "new34_roi2"
    },
    {
      "a_region": "normal_pz_s2",
      "snr": 376.87033579203336,
      "patient_key": "new38",
      "gs": "3+4",
      "target": "2",
      "patient_age": "NaN",
      "diffusivities": [
        0.25,
        0.5,
        0.75,
        1.0,
        1.25,
        1.5,
        2.0,
        2.5,
        3.0,
        20.0
      ],
      "hdf5_dataset": "new38_roi2"
    },
    {
      "a_region": "normal_pz_s2",
      "snr": 306.9507289452169,
      "patient_key": "new39",
      "gs": "nan",
      "target": "nan",
      "patient_age": "NaN",
      "diffusivities": [
        0.25,
        0.5,
        0.75,
        1.0,
        1.25,
        1.5,
        2.0,
        2.5,
        3.0,
        20.0
      ],
      "hdf5_dataset": "new39_roi2"
    },
    {
      "a_region": "normal_pz_s2",
      "snr": 429.2071178347349,
      "patient_key": "new49",
      "gs": "3+4",
      "target": "2",
      "patient_age": "NaN",
      "diffusivities": [
        0.25,
        0.5,
        0.75,
        1.0,
        1.25,
        1.5,
        2.0,
        2.5,
        3.0,
        20.0
      ],
      "hdf5_dataset": "new49_roi2"
    },
    {
      "a_region": "normal_pz_s2",
      "snr": 361.6369035372358,
      "patient_key": "new50",
      "gs": "3+4",
      "target": "2",
      "patient_age": "NaN",
      "diffusivities": [
        0.25,
        0.5,
        0.75,
        1.0,
        1.25,
        1.5,
        2.0,
        2.5,
        3.0,
        20.0
      ],
      "hdf5_dataset": "new50_roi2"
    },
    {
      "a_region": "normal_pz_s2",
      "snr": 465.36276172465716,
      "patient_key": "new51",
      "gs": "3+3",
      "target": "1",
      "patient_age": "NaN",
      "diffusivities": [
        0.25,
        0.5,
        0.75,
        1.0,
        1.25,
        1.5,
        2.0,
        2.5,
        3.0,
        20.0
      ],
      "hdf5_dataset": "new51_roi2"
    },
    {
      "a_region": "normal_pz_s2",
      "snr": 251.55764746872634,
      "patient_key": "new52",
      "gs": "nan",
      "target": "nan",
      "patient_age": "NaN",
      "diffusivities": [
        0.25,
        0.5,
        0.75,
        1.0,
        1.25,
        1.5,
        2.0,
        2.5,
        3.0,
        20.0
      ],
      "hdf5_dataset": "new52_roi2"
    },
    {
      "a_region": "normal_pz_s2",
      "snr": 265.1650429449553,
      "patient_key": "new54",
      "gs": "3+3",
      "target": "1",
      "patient_age": "NaN",
      "diffusivities": [
        0.25,
        0.5,
        0.75,
        1.0,
        1.25,
        1.5,
        2.0,
        2.5,
        3.0,
        20.0
      ],
      "hdf5_dataset": "new54_roi2"
    },
    {
      "a_region": "normal_pz_s2",
      "snr": 733.8894671542847,
      "patient_key": "new55",
      "gs": "4+4",
      "target": "4",
      "patient_age": "NaN",
      "diffusivities": [
        0.25,
        0.5,
        0.75,
        1.0,
        1.25,
        1.5,
        2.0,
        2.5,
        3.0,
        20.0
      ],
      "hdf5_dataset": "new55_roi2"
    },
    {
      "a_region": "normal_pz_s2",
      "snr": 376.87033579203336,
      "patient_key": "new59",
      "gs": "3+4",
      "target": "2",
      "patient_age": "NaN",
      "diffusivities": [
        0.25,
        0.5,
        0.75,
        1.0,
        1.25,
        1.5,
        2.0,
        2.5,
        3.0,
        20.0
      ],
      "hdf5_dataset": "new59_roi2"
    },
    {
      "a_region": "normal_pz_s2",
      "snr": 369.3321675673539,
      "patient_key": "new61",
      "gs": "3+3",
      "target": "1",
      "patient_age": "NaN",
      "diffusivities": [
        0.25,
        0.5,
        0.75,
        1.0,
        1.25,
        1.5,
        2.0,
        2.5,
        3.0,
        20.0
      ],
      "hdf5_dataset": "new61_roi2"
    },
    {
      "a_region": "normal_pz_s2",
      "snr": 687.386354243376,
      "patient_key": "new62",
      "gs": "3+3",
      "target": "1",
      "patient_age": "NaN",
      "diffusivities": [
        0.25,
        0.5,
        0.75,
        1.0,
        1.25,
        1.5,
        2.0,
        2.5,
        3.0,
        20.0
      ],
      "hdf5_dataset": "new62_roi2"
    },
    {
      "a_region": "normal_pz_s2",
      "snr": 438.92624665198593,
      "patient_key": "new63",
      "gs": "3+4",
      "target": "2",
      "patient_age": "NaN",
      "diffusivities": [
        0.25,
        0.5,
        0.75,
        1.0,
        1.25,
        1.5,
        2.0,
        2.5,
        3.0,
        20.0
      ],
      "hdf5_dataset": "new63_roi2"
    }
  ],
  "normal_tz_s3": [
    {
      "a_region": "normal_tz_s3",
      "snr": 548.5777064372922,
      "patient_key": "new01",
      "gs": "4+3",
      "target": "3",
      "patient_age": "NaN",
      "diffusivities": [
        0.25,
        0.5,
        0.75,
        1.0,
        1.25,
        1.5,
        2.0,
        2.5,
        3.0,
        20.0
      ],
      "hdf5_dataset": "new01_roi3"
    },
    {
      "a_region": "normal_tz_s3",
      "snr": 460.80771477916903,
      "patient_key": "new05",
      "gs": "4+3",
      "target": "3",
      "patient_age": "NaN",
      "diffusivities": [
        0.25,
        0.5,
        0.75,
        1.0,
        1.25,
        1.5,
        2.0,
        2.5,
        3.0,
        20.0
      ],
      "hdf5_dataset": "new05_roi3"
    },
    {
      "a_region": "normal_tz_s3",
      "snr": 919.3238004098447,
      "patient_key": "new14",
      "gs": "0+0",
      "target": "0",
      "patient_age": "NaN",
      "diffusivities": [
        0.25,
        0.5,
        0.75,
        1.0,
        1.25,
        1.5,
        2.0,
        2.5,
        3.0,
        20.0
      ],
      "hdf5_dataset": "new14_roi3"
    },
    {
      "a_region": "normal_tz_s3",
      "snr": 536.9182898728633,
      "patient_key": "new17",
      "gs": "0+0",
      "target": "0",
      "patient_age": "NaN",
      "diffusivities": [
        0.25,
        0.5,
        0.75,
        1.0,
        1.25,
        1.5,
        2.0,
        2.5,
        3.0,
        20.0
      ],
      "hdf5_dataset": "new17_roi3"
    },
    {
      "a_region": "normal_tz_s3",
      "snr": 694.5097191544551,
      "patient_key": "new20",
      "gs": "3+3",
      "target": "1",
      "patient_age": "NaN",
      "diffusivities": [
        0.25,
        0.5,
        0.75,
        1.0,
        1.25,
        1.5,
        2.0,
        2.5,
        3.0,
        20.0
      ],
      "hdf5_dataset": "new20_roi3"
    },
    {
      "a_region": "normal_tz_s3",
      "snr": 766.6893112597827,
      "patient_key": "new25",
      "gs": "0+0",
      "target": "0",
      "patient_age": "NaN",
      "diffusivities": [
        0.25,
        0.5,
        0.75,
        1.0,
        1.25,
        1.5,
        2.0,
        2.5,
        3.0,
        20.0
      ],
      "hdf5_dataset": "new25_roi3"
    },
    {
      "a_region": "normal_tz_s3",
      "snr": 511.4318136369696,
      "patient_key": "new28",
      "gs": "3+5",
      "target": "4",
      "patient_age": "NaN",
      "diffusivities": [
        0.25,
        0.5,
        0.75,
        1.0,
        1.25,
        1.5,
        2.0,
        2.5,
        3.0,
        20.0
      ],
      "hdf5_dataset": "new28_roi3"
    },
    {
      "a_region": "normal_tz_s3",
      "snr": 419.2627457812106,
      "patient_key": "new36",
      "gs": "4+3",
      "target": "3",
      "patient_age": "NaN",
      "diffusivities": [
        0.25,
        0.5,
        0.75,
        1.0,
        1.25,
        1.5,
        2.0,
        2.5,
        3.0,
        20.0
      ],
      "hdf5_dataset": "new36_roi3"
    },
    {
      "a_region": "normal_tz_s3",
      "snr": 536.9182898728633,
      "patient_key": "new44",
      "gs": "3+4",
      "target": "2",
      "patient_age": "NaN",
      "diffusivities": [
        0.25,
        0.5,
        0.75,
        1.0,
        1.25,
        1.5,
        2.0,
        2.5,
        3.0,
        20.0
      ],
      "hdf5_dataset": "new44_roi3"
    },
    {
      "a_region": "normal_tz_s3",
      "snr": 318.19805153394634,
      "patient_key": "new45",
      "gs": "4+3+5",
      "target": "5",
      "patient_age": "NaN",
      "diffusivities": [
        0.25,
        0.5,
        0.75,
        1.0,
        1.25,
        1.5,
        2.0,
        2.5,
        3.0,
        20.0
      ],
      "hdf5_dataset": "new45_roi3"
    },
    {
      "a_region": "normal_tz_s3",
      "snr": 865.7547285461396,
      "patient_key": "new46",
      "gs": "0+0",
      "target": "0",
      "patient_age": "NaN",
      "diffusivities": [
        0.25,
        0.5,
        0.75,
        1.0,
        1.25,
        1.5,
        2.0,
        2.5,
        3.0,
        20.0
      ],
      "hdf5_dataset": "new46_roi3"
    },
    {
      "a_region": "normal_tz_s3",
      "snr": 373.1202889149825,
      "patient_key": "new47",
      "gs": "3+4",
      "target": "2",
      "patient_age": "NaN",
      "diffusivities": [
        0.25,
        0.5,
        0.75,
        1.0,
        1.25,
        1.5,
        2.0,
        2.5,
        3.0,
        20.0
      ],
      "hdf5_dataset": "new47_roi3"
    },
    {
      "a_region": "normal_tz_s3",
      "snr": 483.1537022521922,
      "patient_key": "new53",
      "gs": "NaN",
      "target": "NaN",
      "patient_age": "NaN",
      "diffusivities": [
        0.25,
        0.5,
        0.75,
        1.0,
        1.25,
        1.5,
        2.0,
        2.5,
        3.0,
        20.0
      ],
      "hdf5_dataset": "new53_roi3"
    }
  ],
  "tumor_pz_s1": [
    {
      "a_region": "tumor_pz_s1",
      "snr": 369.3321675673539,
      "patient_key": "new02",
      "gs": "4+3",
      "target": "3",
      "patient_age": "NaN",
      "diffusivities": [
        0.25,
        0.5,
        0.75,
        1.0,
        1.25,
        1.5,
        2.0,
        2.5,
        3.0,
        20.0
      ],
      "hdf5_dataset": "new02_roi1"
    },
    {
      "a_region": "tumor_pz_s1",
      "snr": 566.2375826453062,
      "patient_key": "new03",
      "gs": "4+3+5",
      "target": "5",
      "patient_age": "NaN",
      "diffusivities": [
        0.25,
        0.5,
        0.75,
        1.0,
        1.25,
        1.5,
        2.0,
        2.5,
        3.0,
        20.0
      ],
      "hdf5_dataset": "new03_roi1"
    },
    {
      "a_region": "tumor_pz_s1",
      "snr": 221.8529918662356,
      "patient_key": "new04",
      "gs": "3+4",
      "target": "2",
      "patient_age": "NaN",
      "diffusivities": [
        0.25,
        0.5,
        0.75,
        1.0,
        1.25,
        1.5,
        2.0,
        2.5,
        3.0,
        20.0
      ],
      "hdf5_dataset": "new04_roi1"
    },
    {
      "a_region": "tumor_pz_s1",
      "snr": 331.1910324872943,
      "patient_key": "new07",
      "gs": "3+3",
      "target": "1",
      "patient_age": "NaN",
      "diffusivities": [
        0.25,
        0.5,
        0.75,
        1.0,
        1.25,
        1.5,
        2.0,
        2.5,
        3.0,
        20.0
      ],
      "hdf5_dataset": "new07_roi1"
    },
    {
      "a_region": "tumor_pz_s1",
      "snr": 429.2071178347349,
      "patient_key": "new12",
      "gs": "hgpin",
      "target": "hgpin",
      "patient_age": "NaN",
      "diffusivities": [
        0.25,
        0.5,
        0.75,
        1.0,
        1.25,
        1.5,
        2.0,
        2.5,
        3.0,
        20.0
      ],
      "hdf5_dataset": "new12_roi1"
    },
    {
      "a_region": "tumor_pz_s1",
      "snr": 333.30729064933456,
      "patient_key": "new16",
      "gs": "3+4",
      "target": "2",
      "patient_age": "NaN",
      "diffusivities": [
        0.25,
        0.5,
        0.75,
        1.0,
        1.25,
        1.5,
        2.0,
        2.5,
        3.0,
        20.0
      ],
      "hdf5_dataset": "new16_roi1"
    },
    {
      "a_region": "tumor_pz_s1",
      "snr": 329.0611645272046,
      "patient_key": "new18",
      "gs": "4+3",
      "target": "3",
      "patient_age": "NaN",
      "diffusivities": [
        0.25,
        0.5,
        0.75,
        1.0,
        1.25,
        1.5,
        2.0,
        2.5,
        3.0,
        20.0
      ],
      "hdf5_dataset": "new18_roi1"
    },
    {
      "a_region": "tumor_pz_s1",
      "snr": 472.85700798444344,
      "patient_key": "new21",
      "gs": "3+4",
      "target": "2",
      "patient_age": "NaN",
      "diffusivities": [
        0.25,
        0.5,
        0.75,
        1.0,
        1.25,
        1.5,
        2.0,
        2.5,
        3.0,
        20.0
      ],
      "hdf5_dataset": "new21_roi1"
    },
    {
      "a_region": "tumor_pz_s1",
      "snr": 619.6016865696864,
      "patient_key": "new22",
      "gs": "0+0",
      "target": "0",
      "patient_age": "NaN",
      "diffusivities": [
        0.25,
        0.5,
        0.75,
        1.0,
        1.25,
        1.5,
        2.0,
        2.5,
        3.0,
        20.0
      ],
      "hdf5_dataset": "new22_roi1"
    },
    {
      "a_region": "tumor_pz_s1",
      "snr": 254.33737436719755,
      "patient_key": "new23",
      "gs": "0+0",
      "target": "0",
      "patient_age": "NaN",
      "diffusivities": [
        0.25,
        0.5,
        0.75,
        1.0,
        1.25,
        1.5,
        2.0,
        2.5,
        3.0,
        20.0
      ],
      "hdf5_dataset": "new23_roi1"
    },
    {
      "a_region": "tumor_pz_s1",
      "snr": 194.8557158514987,
      "patient_key": "new24",
      "gs": "0+0",
      "target": "0",
      "patient_age": "NaN",
      "diffusivities": [
        0.25,
        0.5,
        0.75,
        1.0,
        1.25,
        1.5,
        2.0,
        2.5,
        3.0,
        20.0
      ],
      "hdf5_dataset": "new24_roi1"
    },
    {
      "a_region": "tumor_pz_s1",
      "snr": 331.1910324872943,
      "patient_key": "new26",
      "gs": "nan",
      "target": "nan",
      "patient_age": "NaN",
      "diffusivities": [
        0.25,
        0.5,
        0.75,
        1.0,
        1.25,
        1.5,
        2.0,
        2.5,
        3.0,
        20.0
      ],
      "hdf5_dataset": "new26_roi1"
    },
    {
      "a_region": "tumor_pz_s1",
      "snr": 318.19805153394634,
      "patient_key": "new30",
      "gs": "3+4",
      "target": "2",
      "patient_age": "NaN",
      "diffusivities": [
        0.25,
        0.5,
        0.75,
        1.0,
        1.25,
        1.5,
        2.0,
        2.5,
        3.0,
        20.0
      ],
      "hdf5_dataset": "new30_roi1"
    },
    {
      "a_region": "tumor_pz_s1",
      "snr": 631.9612329882269,
      "patient_key": "new33",
      "gs": "3+3",
      "target": "1",
      "patient_age": "NaN",
      "diffusivities": [
        0.25,
        0.5,
        0.75,
        1.0,
        1.25,
        1.5,
        2.0,
        2.5,
        3.0,
        20.0
      ],
      "hdf5_dataset": "new33_roi1"
    },
    {
      "a_region": "tumor_pz_s1",
      "snr": 405.6245184896988,
      "patient_key": "new34",
      "gs": "3+4",
      "target": "2",
      "patient_age": "NaN",
      "diffusivities": [
        0.25,
        0.5,
        0.75,
        1.0,
        1.25,
        1.5,
        2.0,
        2.5,
        3.0,
        20.0
      ],
      "hdf5_dataset": "new34_roi1"
    },
    {
      "a_region": "tumor_pz_s1",
      "snr": 335.4101966249685,
      "patient_key": "new38",
      "gs": "3+4",
      "target": "2",
      "patient_age": "NaN",
      "diffusivities": [
        0.25,
        0.5,
        0.75,
        1.0,
        1.25,
        1.5,
        2.0,
        2.5,
        3.0,
        20.0
      ],
      "hdf5_dataset": "new38_roi1"
    },
    {
      "a_region": "tumor_pz_s1",
      "snr": 331.1910324872943,
      "patient_key": "new39",
      "gs": "nan",
      "target": "nan",
      "patient_age": "NaN",
      "diffusivities": [
        0.25,
        0.5,
        0.75,
        1.0,
        1.25,
        1.5,
        2.0,
        2.5,
        3.0,
        20.0
      ],
      "hdf5_dataset": "new39_roi1"
    },
    {
      "a_region": "tumor_pz_s1",
      "snr": 254.33737436719755,
      "patient_key": "new49",
      "gs": "3+4",
      "target": "2",
      "patient_age": "NaN",
      "diffusivities": [
        0.25,
        0.5,
        0.75,
        1.0,
        1.25,
        1.5,
        2.0,
        2.5,
        3.0,
        20.0
      ],
      "hdf5_dataset": "new49_roi1"
    },
    {
      "a_region": "tumor_pz_s1",
      "snr": 187.5,
      "patient_key": "new50",
      "gs": "3+4",
      "target": "2",
      "patient_age": "NaN",
      "diffusivities": [
        0.25,
        0.5,
        0.75,
        1.0,
        1.25,
        1.5,
        2.0,
        2.5,
        3.0,
        20.0
      ],
      "hdf5_dataset": "new50_roi1"
    },
    {
      "a_region": "tumor_pz_s1",
      "snr": 245.903944661325,
      "patient_key": "new51",
      "gs": "3+3",
      "target": "1",
      "patient_age": "NaN",
      "diffusivities": [
        0.25,
        0.5,
        0.75,
        1.0,
        1.25,
        1.5,
        2.0,
        2.5,
        3.0,
        20.0
      ],
      "hdf5_dataset": "new51_roi1"
    },
    {
      "a_region": "tumor_pz_s1",
      "snr": 140.3121520040228,
      "patient_key": "new52",
      "gs": "nan",
      "target": "nan",
      "patient_age": "NaN",
      "diffusivities": [
        0.25,
        0.5,
        0.75,
        1.0,
        1.25,
        1.5,
        2.0,
        2.5,
        3.0,
        20.0
      ],
      "hdf5_dataset": "new52_roi1"
    },
    {
      "a_region": "tumor_pz_s1",
      "snr": 191.2132317597294,
      "patient_key": "new54",
      "gs": "3+3",
      "target": "1",
      "patient_age": "NaN",
      "diffusivities": [
        0.25,
        0.5,
        0.75,
        1.0,
        1.25,
        1.5,
        2.0,
        2.5,
        3.0,
        20.0
      ],
      "hdf5_dataset": "new54_roi1"
    },
    {
      "a_region": "tumor_pz_s1",
      "snr": 1228.9477206130455,
      "patient_key": "new55",
      "gs": "4+4",
      "target": "4",
      "patient_age": "NaN",
      "diffusivities": [
        0.25,
        0.5,
        0.75,
        1.0,
        1.25,
        1.5,
        2.0,
        2.5,
        3.0,
        20.0
      ],
      "hdf5_dataset": "new55_roi1"
    },
    {
      "a_region": "tumor_pz_s1",
      "snr": 225.0,
      "patient_key": "new59",
      "gs": "3+4",
      "target": "2",
      "patient_age": "NaN",
      "diffusivities": [
        0.25,
        0.5,
        0.75,
        1.0,
        1.25,
        1.5,
        2.0,
        2.5,
        3.0,
        20.0
      ],
      "hdf5_dataset": "new59_roi1"
    },
    {
      "a_region": "tumor_pz_s1",
      "snr": 578.5218232703068,
      "patient_key": "new61",
      "gs": "3+3",
      "target": "1",
      "patient_age": "NaN",
      "diffusivities": [
        0.25,
        0.5,
        0.75,
        1.0,
        1.25,
        1.5,
        2.0,
        2.5,
        3.0,
        20.0
      ],
      "hdf5_dataset": "new61_roi1"
    },
    {
      "a_region": "tumor_pz_s1",
      "snr": 292.8843628464995,
      "patient_key": "new62",
      "gs": "3+3",
      "target": "1",
      "patient_age": "NaN",
      "diffusivities": [
        0.25,
        0.5,
        0.75,
        1.0,
        1.25,
        1.5,
        2.0,
        2.5,
        3.0,
        20.0
      ],
      "hdf5_dataset": "new62_roi1"
    },
    {
      "a_region": "tumor_pz_s1",
      "snr": 331.1910324872943,
      "patient_key": "new63",
      "gs": "3+4",
      "target": "2",
      "patient_age": "NaN",
      "diffusivities": [
        0.25,
        0.5,
        0.75,
        1.0,
        1.25,
        1.5,
        2.0,
        2.5,
        3.0,
        20.0
      ],
      "hdf5_dataset": "new63_roi1"
    }
  ],
  "tumor_tz_s1": [
    {
      "a_region": "tumor_tz_s1",
      "snr": 434.0938838546335,
      "patient_key": "new01",
      "gs": "4+3",
      "target": "3",
      "patient_age": "NaN",
      "diffusivities": [
        0.25,
        0.5,
        0.75,
        1.0,
        1.25,
        1.5,
        2.0,
        2.5,
        3.0,
        20.0
      ],
      "hdf5_dataset": "new01_roi1"
    },
    {
      "a_region": "tumor_tz_s1",
      "snr": 414.2010381445223,
      "patient_key": "new05",
      "gs": "4+3",
      "target": "3",
      "patient_age": "NaN",
      "diffusivities": [
        0.25,
        0.5,
        0.75,
        1.0,
        1.25,
        1.5,
        2.0,
        2.5,
        3.0,
        20.0
      ],
      "hdf5_dataset": "new05_roi1"
    },
    {
      "a_region": "tumor_tz_s1",
      "snr": 463.8493828819868,
      "patient_key": "new14",
      "gs": "0+0",
      "target": "0",
      "patient_age": "NaN",
      "diffusivities": [
        0.25,
        0.5,
        0.75,
        1.0,
        1.25,
        1.5,
        2.0,
        2.5,
        3.0,
        20.0
      ],
      "hdf5_dataset": "new14_roi1"
    },
    {
      "a_region": "tumor_tz_s1",
      "snr": 507.2905971925756,
      "patient_key": "new17",
      "gs": "0+0",
      "target": "0",
      "patient_age": "NaN",
      "diffusivities": [
        0.25,
        0.5,
        0.75,
        1.0,
        1.25,
        1.5,
        2.0,
        2.5,
        3.0,
        20.0
      ],
      "hdf5_dataset": "new17_roi1"
    },
    {
      "a_region": "tumor_tz_s1",
      "snr": 343.693177121688,
      "patient_key": "new20",
      "gs": "3+3",
      "target": "1",
      "patient_age": "NaN",
      "diffusivities": [
        0.25,
        0.5,
        0.75,
        1.0,
        1.25,
        1.5,
        2.0,
        2.5,
        3.0,
        20.0
      ],
      "hdf5_dataset": "new20_roi1"
    },
    {
      "a_region": "tumor_tz_s1",
      "snr": 163.45871038277528,
      "patient_key": "new25",
      "gs": "0+0",
      "target": "0",
      "patient_age": "NaN",
      "diffusivities": [
        0.25,
        0.5,
        0.75,
        1.0,
        1.25,
        1.5,
        2.0,
        2.5,
        3.0,
        20.0
      ],
      "hdf5_dataset": "new25_roi1"
    },
    {
      "a_region": "tumor_tz_s1",
      "snr": 497.49371855331,
      "patient_key": "new28",
      "gs": "3+5",
      "target": "4",
      "patient_age": "NaN",
      "diffusivities": [
        0.25,
        0.5,
        0.75,
        1.0,
        1.25,
        1.5,
        2.0,
        2.5,
        3.0,
        20.0
      ],
      "hdf5_dataset": "new28_roi1"
    },
    {
      "a_region": "tumor_tz_s1",
      "snr": 285.5914914698966,
      "patient_key": "new36",
      "gs": "4+3",
      "target": "3",
      "patient_age": "NaN",
      "diffusivities": [
        0.25,
        0.5,
        0.75,
        1.0,
        1.25,
        1.5,
        2.0,
        2.5,
        3.0,
        20.0
      ],
      "hdf5_dataset": "new36_roi1"
    },
    {
      "a_region": "tumor_tz_s1",
      "snr": 466.8712349245775,
      "patient_key": "new44",
      "gs": "3+4",
      "target": "2",
      "patient_age": "NaN",
      "diffusivities": [
        0.25,
        0.5,
        0.75,
        1.0,
        1.25,
        1.5,
        2.0,
        2.5,
        3.0,
        20.0
      ],
      "hdf5_dataset": "new44_roi1"
    },
    {
      "a_region": "tumor_tz_s1",
      "snr": 477.29707730091957,
      "patient_key": "new45",
      "gs": "4+3+5",
      "target": "5",
      "patient_age": "NaN",
      "diffusivities": [
        0.25,
        0.5,
        0.75,
        1.0,
        1.25,
        1.5,
        2.0,
        2.5,
        3.0,
        20.0
      ],
      "hdf5_dataset": "new45_roi1"
    },
    {
      "a_region": "tumor_tz_s1",
      "snr": 503.1152949374527,
      "patient_key": "new46",
      "gs": "0+0",
      "target": "0",
      "patient_age": "NaN",
      "diffusivities": [
        0.25,
        0.5,
        0.75,
        1.0,
        1.25,
        1.5,
        2.0,
        2.5,
        3.0,
        20.0
      ],
      "hdf5_dataset": "new46_roi1"
    },
    {
      "a_region": "tumor_tz_s1",
      "snr": 462.3310502226732,
      "patient_key": "new47",
      "gs": "3+4",
      "target": "2",
      "patient_age": "NaN",
      "diffusivities": [
        0.25,
        0.5,
        0.75,
        1.0,
        1.25,
        1.5,
        2.0,
        2.5,
        3.0,
        20.0
      ],
      "hdf5_dataset": "new47_roi1"
    },
    {
      "a_region": "tumor_tz_s1",
      "snr": 459.2793267718459,
      "patient_key": "new53",
      "gs": "NaN",
      "target": "NaN",
      "patient_age": "NaN",
      "diffusivities": [
        0.25,
        0.5,
        0.75,
        1.0,
        1.25,
        1.5,
        2.0,
        2.5,
        3.0,
        20.0
      ],
      "hdf5_dataset": "new53_roi1"
    }
  ],
  "Neglected!": []
}